flexrest
