Metadata-Version: 1.1
Name: flexrest
Version: 0.1.9
Summary: Flexible Flask Rest Api
Home-page: https://github.com/pprolancer/flexrest
Author: pprolancer
Author-email: pprolancer@gmail.com
License: UNKNOWN
Download-URL: https://github.com/pprolancer/flexrest/tarball/0.1.9
Keywords: api,rest,restful
Platform: UNKNOWN
